Workbook

Sheet Data_Base
A1: Mes | B1: Presupuesto Planificado Acumulado (PV) | C1: Costo Real Acumulado (AC) | D1: % Avance Físico Real | E1: Indicador OTIF (%) | F1: Trazabilidad (%) | G1: Discrepancia Inventario (%) | H1: Pérdidas Mermas (USD) | I1: Cumplimiento Proveedores (%) | J1: Reclamos Clientes
A2: Línea Base | B2: 0 | C2: 0 | D2: 0 | E2: 0.81 | F2: 0.58 | G2: 8,4% | H2: 23500 | I2: 0.72 | J2: 162
A3: Mes 1 | B3: 180000 | C3: 165000 | D3: 0.1 | E3: 82,5% | F3: 0.62 | G3: 7,1% | H3: 19800 | I3: 0.74 | J3: 145
A4: Mes 2 | B4: 360000 | C4: 335000 | D4: 0.2 | E4: 0.84 | F4: 0.66 | G4: 0.06 | H4: 16500 | I4: 0.76 | J4: 128
A5: Mes 3 | B5: 550000 | C5: 512000 | D5: 0.3 | E5: 85,5% | F5: 0.71 | G5: 5,2% | H5: 14200 | I5: 0.79 | J5: 110

Sheet Calculos_EVM
A1: Parámetro | B1: Valor
A2: Presupuesto Hasta la Conclusión (BAC) | B2: 1480000
A3: Reserva de Contingencia Disponible | B3: 105000
A4: Reserva de Gestión Disponible | B4: 78000
A6: Métrica EVM | B6: Valor
A7: Valor Planificado (PV) | B7: =Data_Base!B5 -> 550000
A8: Costo Real (AC) | B8: =Data_Base!C5 -> 512000
A9: Valor Ganado (EV) | B9: =B2*Data_Base!D5 -> 444000
A10: Variación del Cronograma (SV) | B10: =B9-B7 -> -106000
A11: Índice Desempeño Cronograma (SPI) | B11: =B9/B7 -> 0.80727273
A12: Variación del Costo (CV) | B12: =B9-B8 -> -68000
A13: Índice Desempeño Costo (CPI) | B13: =B9/B8 -> 0.8671875
A14: Estimación a la Conclusión (EAC) | B14: =B2/B13 -> 1706666.7
A15: Variación a la Conclusión (VAC) | B15: =B2-B14 -> -226666.67

Sheet Dashboard_Ejecutivo
A1: BAC | C1: EV | E1: SPI | G1: CPI | I1: No | J1: Indicador | K1: Valor Actual | L1: Meta | M1: Estado | N1: Interpretación | O1: Umbral | P1: Decisión Sugerida
A2: PRESUPUESTO TOTAL | C2: VALOR GANADO | E2: CRONOGRAMA | G2: COSTO | I2: 1 | J2: SPI (Desempeño Cronograma) | K2: =+Calculos_EVM!B11 -> 0.80727273 | L2: 1 | M2: =IF(K2>=1, "Verde", IF(K2>=0.9, "Amarillo", "Rojo")) -> Rojo | N2: Retraso de 19,3% en entregables técnicos | O2: SPI < 0,90 | P2: Replanificar y/o aplicar crashing
A3: =Calculos_EVM!B2 -> 1480000 | C3: =Calculos_EVM!B9 -> 444000 | E3: =Calculos_EVM!B11 -> 0.80727273 | G3: =Calculos_EVM!B13 -> 0.8671875 | I3: =+I2+1 -> 2 | J3: CPI (Desempeño Financiero) | K3: =+Calculos_EVM!B13 -> 0.8671875 | L3: 1 | M3: =IF(K3>=1, "Verde", IF(K3>=0.92, "Amarillo", "Rojo")) -> Rojo | N3: Sobrecosto acumulado por reprocesos | O3: CPI < 0,92 | P3: Auditar horas de consultoría
I4: =+I3+1 -> 3 | J4: OTIF (Entregas Completas/Tiempo) | K4: 0.855 | L4: 0.94 | M4: =IF(K4>=0.94, "Verde", IF(K4>=0.88, "Amarillo", "Rojo")) -> Rojo | N4: Mejora frente a línea base, por debajo de meta | O4: OTIF < 88% | P4: Reconfigurar rutas
I5: =+I4+1 -> 4 | J5: Trazabilidad de Pedidos | K5: =+Data_Base!F5 -> 0.71 | L5: 0.95 | M5: =IF(K5>=0.95, "Verde", IF(K5>=0.8, "Amarillo", "Rojo")) -> Rojo | N5: Brecha en flota contratada | O5: Trazabilidad < 80% | P5: Exigir uso de App móvil
I6: =+I5+1 -> 5 | J6: Discrepancia Inventario | K6: =+Data_Base!G5 -> 5,2% | L6: 2,5% | M6: =IF(K6<=0.025, "Verde", IF(K6<=0.04, "Amarillo", "Rojo")) -> Rojo | N6: Reducción progresiva del error | O6: Discrepancia > 4% | P6: Implementar conteos cíclicos
I7: =+I6+1 -> 6 | J7: Pérdidas por Mermas | K7: =+Data_Base!H5 -> 14200 | L7: $8.500 | M7: =IF(K7<=8500, "Verde", IF(K7<=12000, "Amarillo", "Rojo")) -> Rojo | N7: Cadena de frío presenta vulnerabilidad | O7: Pérdida > $12.000 | P7: Instalar sensores IoT de frío
I8: =+I7+1 -> 7 | J8: Cumplimiento Proveedores | K8: =+Data_Base!I5 -> 0.79 | L8: 0.96 | M8: =IF(K8>=0.96, "Verde", IF(K8>=0.85, "Amarillo", "Rojo")) -> Rojo | N8: Alta variabilidad documental | O8: Cumplimiento < 85% | P8: Notificación y suspensión de pagos
I9: =+I8+1 -> 8 | J9: Reclamos Clientes | K9: =+Data_Base!J5 -> 110 | L9: 60 | M9: =IF(K9<=60, "Verde", IF(K9<=90, "Amarillo", "Rojo")) -> Rojo | N9: Disminución relevante de reclamos | O9: Reclamos > 90 | P9: Publicar tablero de pedidos
